widefield_plate_solver/__init__.py
widefield_plate_solver/api_solver.py
widefield_plate_solver/exceptions.py
widefield_plate_solver/extract_stars.py
widefield_plate_solver/local_solver.py
widefield_plate_solver/plotter.py
widefield_plate_solver/script.py
widefield_plate_solver-0.1.4.data/scripts/script.py
widefield_plate_solver-0.1.4.dist-info/METADATA
widefield_plate_solver-0.1.4.dist-info/WHEEL
widefield_plate_solver-0.1.4.dist-info/entry_points.txt
widefield_plate_solver-0.1.4.dist-info/top_level.txt
widefield_plate_solver-0.1.4.dist-info/RECORD
