Metadata-Version: 2.1
Name: widefield_plate_solver
Version: 0.1.4
Summary: An astronomical image plate solving package.
Home-page: http://pypi.python.org/pypi/widefield_plate_solver/
Author: Frédéric Dux
Author-email: duxfrederic@gmail.com
License: LICENSE.txt
Requires-Dist: scipy
Requires-Dist: astropy
Requires-Dist: sep
Requires-Dist: matplotlib
Requires-Dist: astroquery
Requires-Dist: requests
